odoo8_addon_account_invoice_import_invoice2data-8.0.1.0.0.99.dev16-nspkg.pth
odoo_addons/account_invoice_import_invoice2data/README.rst
odoo_addons/account_invoice_import_invoice2data/__init__.py
odoo_addons/account_invoice_import_invoice2data/__openerp__.py
odoo_addons/account_invoice_import_invoice2data/demo/demo_data.xml
odoo_addons/account_invoice_import_invoice2data/i18n/account_invoice_import_invoice2data.pot
odoo_addons/account_invoice_import_invoice2data/i18n/sl.po
odoo_addons/account_invoice_import_invoice2data/static/description/icon.png
odoo_addons/account_invoice_import_invoice2data/tests/__init__.py
odoo_addons/account_invoice_import_invoice2data/tests/test_invoice_import.py
odoo_addons/account_invoice_import_invoice2data/tests/pdf/invoice_free_fiber_201507.pdf
odoo_addons/account_invoice_import_invoice2data/wizard/__init__.py
odoo_addons/account_invoice_import_invoice2data/wizard/account_invoice_import.py
odoo8_addon_account_invoice_import_invoice2data-8.0.1.0.0.99.dev16.dist-info/METADATA
odoo8_addon_account_invoice_import_invoice2data-8.0.1.0.0.99.dev16.dist-info/WHEEL
odoo8_addon_account_invoice_import_invoice2data-8.0.1.0.0.99.dev16.dist-info/namespace_packages.txt
odoo8_addon_account_invoice_import_invoice2data-8.0.1.0.0.99.dev16.dist-info/top_level.txt
odoo8_addon_account_invoice_import_invoice2data-8.0.1.0.0.99.dev16.dist-info/RECORD
